{"安徽大学": [{"招生单位": "(10357)安徽大学", "考试方式": "统考", "院系所": "(017)物理与材料科学学院", "跨专业": "", "专业": "(085400)(专业学位)电子信息", "学习方式": "全日制", "研究方向": "(01)光学工程", "指导老师": "", "拟招人数": "专业：25(不含推免)", "备注": "", "考试科目": {"(101)思想政治理论": "见招生简章", "(204)英语二": "见招生简章", "(302)数学二": "见招生简章", "(824)普通物理B": "见招生简章"}}, {"招生单位": "(10357)安徽大学", "考试方式": "统考", "院系所": "(021)电子信息工程学院", "跨专业": "", "专业": "(085400)(专业学位)电子信息", "学习方式": "全日制", "研究方向": "(01)智能信号处理与工程", "指导老师": "", "拟招人数": "专业：150(不含推免)", "备注": "", "考试科目": {"(101)思想政治理论": "见招生简章", "(201)英语一": "见招生简章", "(301)数学一": "见招生简章", "(830)专业基础综合一（信号与系统 、数字电路与?": "见招生简章"}}, {"招生单位": "(10357)安徽大学", "考试方式": "统考", "院系所": "(021)电子信息工程学院", "跨专业": "", "专业": "(085400)(专业学位)电子信息", "学习方式": "全日制", "研究方向": "(02)通信智能系统", "指导老师": "", "拟招人数": "专业：150(不含推免)", "备注": "", "考试科目": {"(101)思想政治理论": "见招生简章", "(201)英语一": "见招生简章", "(301)数学一": "见招生简章", "(830)专业基础综合一（信号与系统 、数字电路与?": "见招生简章"}}, {"招生单位": "(10357)安徽大学", "考试方式": "统考", "院系所": "(021)电子信息工程学院", "跨专业": "", "专业": "(085400)(专业学位)电子信息", "学习方式": "全日制", "研究方向": "(03)射频电路与微波工程", "指导老师": "", "拟招人数": "专业：150(不含推免)", "备注": "", "考试科目": {"(101)思想政治理论": "见招生简章", "(201)英语一": "见招生简章", "(301)数学一": "见招生简章", "(830)专业基础综合一（信号与系统 、数字电路与?": "见招生简章"}}, {"招生单位": "(10357)安徽大学", "考试方式": "统考", "院系所": "(021)电子信息工程学院", "跨专业": "", "专业": "(085400)(专业学位)电子信息", "学习方式": "全日制", "研究方向": "(04)集成电路工程", "指导老师": "", "拟招人数": "专业：150(不含推免)", "备注": "", "考试科目": {"(101)思想政治理论": "见招生简章", "(201)英语一": "见招生简章", "(301)数学一": "见招生简章", "(830)专业基础综合一（信号与系统 、数字电路与?": "见招生简章"}}, {"招生单位": "(10357)安徽大学", "考试方式": "统考", "院系所": "(022)电气工程与自动化学院", "跨专业": "", "专业": "(085400)(专业学位)电子信息", "学习方式": "全日制", "研究方向": "(01)控制工程", "指导老师": "", "拟招人数": "专业：61(不含推免)", "备注": "", "考试科目": {"(101)思想政治理论": "见招生简章", "(201)英语一": "见招生简章", "(301)数学一": "见招生简章", "(831)自动控制理论": "见招生简章"}}, {"招生单位": "(10357)安徽大学", "考试方式": "统考", "院系所": "(022)电气工程与自动化学院", "跨专业": "", "专业": "(085400)(专业学位)电子信息", "学习方式": "全日制", "研究方向": "(02)智能信息处理", "指导老师": "", "拟招人数": "专业：61(不含推免)", "备注": "", "考试科目": {"(101)思想政治理论": "见招生简章", "(201)英语一": "见招生简章", "(301)数学一": "见招生简章", "(831)自动控制理论": "见招生简章"}}, {"招生单位": "(10357)安徽大学", "考试方式": "统考", "院系所": "(022)电气工程与自动化学院", "跨专业": "", "专业": "(085400)(专业学位)电子信息", "学习方式": "全日制", "研究方向": "(03)检测技术及应用", "指导老师": "", "拟招人数": "专业：61(不含推免)", "备注": "", "考试科目": {"(101)思想政治理论": "见招生简章", "(201)英语一": "见招生简章", "(301)数学一": "见招生简章", "(831)自动控制理论": "见招生简章"}}, {"招生单位": "(10357)安徽大学", "考试方式": "统考", "院系所": "(023)计算机科学与技术学院", "跨专业": "", "专业": "(085400)(专业学位)电子信息", "学习方式": "全日制", "研究方向": "(01)计算机技术", "指导老师": "", "拟招人数": "专业：188(不含推免)", "备注": "", "考试科目": {"(101)思想政治理论": "见招生简章", "(201)英语一": "见招生简章", "(301)数学一": "见招生简章", "(834)计算机专业基础（数据结构、操作系统）": "见招生简章"}}, {"招生单位": "(10357)安徽大学", "考试方式": "统考", "院系所": "(023)计算机科学与技术学院", "跨专业": "", "专业": "(085400)(专业学位)电子信息", "学习方式": "全日制", "研究方向": "(02)网络空间安全", "指导老师": "", "拟招人数": "专业：188(不含推免)", "备注": "", "考试科目": {"(101)思想政治理论": "见招生简章", "(201)英语一": "见招生简章", "(301)数学一": "见招生简章", "(834)计算机专业基础（数据结构、操作系统）": "见招生简章"}}, {"招生单位": "(10357)安徽大学", "考试方式": "统考", "院系所": "(023)计算机科学与技术学院", "跨专业": "", "专业": "(085400)(专业学位)电子信息", "学习方式": "全日制", "研究方向": "(03)人工智能", "指导老师": "", "拟招人数": "专业：188(不含推免)", "备注": "", "考试科目": {"(101)思想政治理论": "见招生简章", "(201)英语一": "见招生简章", "(301)数学一": "见招生简章", "(834)计算机专业基础（数据结构、操作系统）": "见招生简章"}}, {"招生单位": "(10357)安徽大学", "考试方式": "统考", "院系所": "(023)计算机科学与技术学院", "跨专业": "", "专业": "(085400)(专业学位)电子信息", "学习方式": "全日制", "研究方向": "(04)软件工程", "指导老师": "", "拟招人数": "专业：188(不含推免)", "备注": "", "考试科目": {"(101)思想政治理论": "见招生简章", "(201)英语一": "见招生简章", "(301)数学一": "见招生简章", "(835)软件工程专业基础（数据结构、高级语言程序": "见招生简章"}}, {"招生单位": "(10357)安徽大学", "考试方式": "统考", "院系所": "(024)物质科学与信息技术研究院", "跨专业": "", "专业": "(085400)(专业学位)电子信息", "学习方式": "全日制", "研究方向": "(01)计算机技术", "指导老师": "", "拟招人数": "专业：17(不含推免)", "备注": "", "考试科目": {"(101)思想政治理论": "见招生简章", "(204)英语二": "见招生简章", "(302)数学二": "见招生简章", "(834)计算机专业基础（数据结构、操作系统）": "见招生简章"}}, {"招生单位": "(10357)安徽大学", "考试方式": "统考", "院系所": "(024)物质科学与信息技术研究院", "跨专业": "", "专业": "(085400)(专业学位)电子信息", "学习方式": "全日制", "研究方向": "(02)进化计算与群体智能", "指导老师": "", "拟招人数": "专业：17(不含推免)", "备注": "", "考试科目": {"(101)思想政治理论": "见招生简章", "(204)英语二": "见招生简章", "(302)数学二": "见招生简章", "(834)计算机专业基础（数据结构、操作系统）": "见招生简章"}}, {"招生单位": "(10357)安徽大学", "考试方式": "统考", "院系所": "(024)物质科学与信息技术研究院", "跨专业": "", "专业": "(085400)(专业学位)电子信息", "学习方式": "全日制", "研究方向": "(03)数据挖掘", "指导老师": "", "拟招人数": "专业：17(不含推免)", "备注": "", "考试科目": {"(101)思想政治理论": "见招生简章", "(204)英语二": "见招生简章", "(302)数学二": "见招生简章", "(834)计算机专业基础（数据结构、操作系统）": "见招生简章"}}, {"招生单位": "(10357)安徽大学", "考试方式": "统考", "院系所": "(024)物质科学与信息技术研究院", "跨专业": "", "专业": "(085400)(专业学位)电子信息", "学习方式": "全日制", "研究方向": "(04)机器学习方法及应用", "指导老师": "", "拟招人数": "专业：17(不含推免)", "备注": "", "考试科目": {"(101)思想政治理论": "见招生简章", "(204)英语二": "见招生简章", "(302)数学二": "见招生简章", "(834)计算机专业基础（数据结构、操作系统）": "见招生简章"}}, {"招生单位": "(10357)安徽大学", "考试方式": "统考", "院系所": "(024)物质科学与信息技术研究院", "跨专业": "", "专业": "(085400)(专业学位)电子信息", "学习方式": "全日制", "研究方向": "(05)图像处理与识别", "指导老师": "", "拟招人数": "专业：17(不含推免)", "备注": "", "考试科目": {"(101)思想政治理论": "见招生简章", "(204)英语二": "见招生简章", "(302)数学二": "见招生简章", "(834)计算机专业基础（数据结构、操作系统）": "见招生简章"}}, {"招生单位": "(10357)安徽大学", "考试方式": "统考", "院系所": "(024)物质科学与信息技术研究院", "跨专业": "", "专业": "(085400)(专业学位)电子信息", "学习方式": "全日制", "研究方向": "(06)人工智能", "指导老师": "", "拟招人数": "专业：17(不含推免)", "备注": "", "考试科目": {"(101)思想政治理论": "见招生简章", "(204)英语二": "见招生简章", "(302)数学二": "见招生简章", "(834)计算机专业基础（数据结构、操作系统）": "见招生简章"}}, {"招生单位": "(10357)安徽大学", "考试方式": "统考", "院系所": "(024)物质科学与信息技术研究院", "跨专业": "", "专业": "(085400)(专业学位)电子信息", "学习方式": "全日制", "研究方向": "(07)软件工程", "指导老师": "", "拟招人数": "专业：17(不含推免)", "备注": "", "考试科目": {"(101)思想政治理论": "见招生简章", "(204)英语二": "见招生简章", "(302)数学二": "见招生简章", "(834)计算机专业基础（数据结构、操作系统）": "见招生简章"}}, {"招生单位": "(10357)安徽大学", "考试方式": "统考", "院系所": "(024)物质科学与信息技术研究院", "跨专业": "", "专业": "(085400)(专业学位)电子信息", "学习方式": "全日制", "研究方向": "(08)检测技术及应用", "指导老师": "", "拟招人数": "专业：17(不含推免)", "备注": "", "考试科目": {"(101)思想政治理论": "见招生简章", "(204)英语二": "见招生简章", "(302)数学二": "见招生简章", "(834)计算机专业基础（数据结构、操作系统）": "见招生简章"}}, {"招生单位": "(10357)安徽大学", "考试方式": "统考", "院系所": "(025)联合培养（中科院合肥物质科学研究院）", "跨专业": "", "专业": "(085400)(专业学位)电子信息", "学习方式": "全日制", "研究方向": "(01)光电检测技术", "指导老师": "", "拟招人数": "专业：47(不含推免)", "备注": "", "考试科目": {"(101)思想政治理论": "见招生简章", "(204)英语二": "见招生简章", "(302)数学二": "见招生简章", "(834)计算机专业基础（数据结构、操作系统）": "见招生简章"}}, {"招生单位": "(10357)安徽大学", "考试方式": "统考", "院系所": "(025)联合培养（中科院合肥物质科学研究院）", "跨专业": "", "专业": "(085400)(专业学位)电子信息", "学习方式": "全日制", "研究方向": "(02)大数据与云计算", "指导老师": "", "拟招人数": "专业：47(不含推免)", "备注": "", "考试科目": {"(101)思想政治理论": "见招生简章", "(204)英语二": "见招生简章", "(302)数学二": "见招生简章", "(834)计算机专业基础（数据结构、操作系统）": "见招生简章"}}, {"招生单位": "(10357)安徽大学", "考试方式": "统考", "院系所": "(025)联合培养（中科院合肥物质科学研究院）", "跨专业": "", "专业": "(085400)(专业学位)电子信息", "学习方式": "全日制", "研究方向": "(03)计算机应用技术", "指导老师": "", "拟招人数": "专业：47(不含推免)", "备注": "", "考试科目": {"(101)思想政治理论": "见招生简章", "(204)英语二": "见招生简章", "(302)数学二": "见招生简章", "(834)计算机专业基础（数据结构、操作系统）": "见招生简章"}}, {"招生单位": "(10357)安徽大学", "考试方式": "统考", "院系所": "(025)联合培养（中科院合肥物质科学研究院）", "跨专业": "", "专业": "(085400)(专业学位)电子信息", "学习方式": "全日制", "研究方向": "(04)视听觉信息处理与模式识别", "指导老师": "", "拟招人数": "专业：47(不含推免)", "备注": "", "考试科目": {"(101)思想政治理论": "见招生简章", "(204)英语二": "见招生简章", "(302)数学二": "见招生简章", "(834)计算机专业基础（数据结构、操作系统）": "见招生简章"}}, {"招生单位": "(10357)安徽大学", "考试方式": "统考", "院系所": "(025)联合培养（中科院合肥物质科学研究院）", "跨专业": "", "专业": "(085400)(专业学位)电子信息", "学习方式": "全日制", "研究方向": "(05)嵌入式系统及可靠性", "指导老师": "", "拟招人数": "专业：47(不含推免)", "备注": "", "考试科目": {"(101)思想政治理论": "见招生简章", "(204)英语二": "见招生简章", "(302)数学二": "见招生简章", "(834)计算机专业基础（数据结构、操作系统）": "见招生简章"}}, {"招生单位": "(10357)安徽大学", "考试方式": "统考", "院系所": "(025)联合培养（中科院合肥物质科学研究院）", "跨专业": "", "专业": "(085400)(专业学位)电子信息", "学习方式": "全日制", "研究方向": "(06)检测技术与智能仪器", "指导老师": "", "拟招人数": "专业：47(不含推免)", "备注": "", "考试科目": {"(101)思想政治理论": "见招生简章", "(204)英语二": "见招生简章", "(302)数学二": "见招生简章", "(834)计算机专业基础（数据结构、操作系统）": "见招生简章"}}, {"招生单位": "(10357)安徽大学", "考试方式": "统考", "院系所": "(025)联合培养（中科院合肥物质科学研究院）", "跨专业": "", "专业": "(085400)(专业学位)电子信息", "学习方式": "全日制", "研究方向": "(07)软件工程", "指导老师": "", "拟招人数": "专业：47(不含推免)", "备注": "", "考试科目": {"(101)思想政治理论": "见招生简章", "(204)英语二": "见招生简章", "(302)数学二": "见招生简章", "(834)计算机专业基础（数据结构、操作系统）": "见招生简章"}}, {"招生单位": "(10357)安徽大学", "考试方式": "统考", "院系所": "(025)联合培养（中科院合肥物质科学研究院）", "跨专业": "", "专业": "(085400)(专业学位)电子信息", "学习方式": "全日制", "研究方向": "(08)物联网技术与智能系统", "指导老师": "", "拟招人数": "专业：47(不含推免)", "备注": "", "考试科目": {"(101)思想政治理论": "见招生简章", "(204)英语二": "见招生简章", "(302)数学二": "见招生简章", "(834)计算机专业基础（数据结构、操作系统）": "见招生简章"}}, {"招生单位": "(10357)安徽大学", "考试方式": "统考", "院系所": "(025)联合培养（中科院合肥物质科学研究院）", "跨专业": "", "专业": "(085400)(专业学位)电子信息", "学习方式": "全日制", "研究方向": "(09)智能机器人", "指导老师": "", "拟招人数": "专业：47(不含推免)", "备注": "", "考试科目": {"(101)思想政治理论": "见招生简章", "(204)英语二": "见招生简章", "(302)数学二": "见招生简章", "(834)计算机专业基础（数据结构、操作系统）": "见招生简章"}}, {"招生单位": "(10357)安徽大学", "考试方式": "统考", "院系所": "(025)联合培养（中科院合肥物质科学研究院）", "跨专业": "", "专业": "(085400)(专业学位)电子信息", "学习方式": "全日制", "研究方向": "(10)人工智能", "指导老师": "", "拟招人数": "专业：47(不含推免)", "备注": "", "考试科目": {"(101)思想政治理论": "见招生简章", "(204)英语二": "见招生简章", "(302)数学二": "见招生简章", "(834)计算机专业基础（数据结构、操作系统）": "见招生简章"}}, {"招生单位": "(10357)安徽大学", "考试方式": "统考", "院系所": "(025)联合培养（中科院合肥物质科学研究院）", "跨专业": "", "专业": "(085400)(专业学位)电子信息", "学习方式": "全日制", "研究方向": "(11)物联网传感器技术", "指导老师": "", "拟招人数": "专业：47(不含推免)", "备注": "", "考试科目": {"(101)思想政治理论": "见招生简章", "(204)英语二": "见招生简章", "(302)数学二": "见招生简章", "(834)计算机专业基础（数据结构、操作系统）": "见招生简章"}}, {"招生单位": "(10357)安徽大学", "考试方式": "统考", "院系所": "(025)联合培养（中科院合肥物质科学研究院）", "跨专业": "", "专业": "(085400)(专业学位)电子信息", "学习方式": "全日制", "研究方向": "(12)仪器仪表工程", "指导老师": "", "拟招人数": "专业：47(不含推免)", "备注": "", "考试科目": {"(101)思想政治理论": "见招生简章", "(204)英语二": "见招生简章", "(302)数学二": "见招生简章", "(834)计算机专业基础（数据结构、操作系统）": "见招生简章"}}, {"招生单位": "(10357)安徽大学", "考试方式": "统考", "院系所": "(025)联合培养（中科院合肥物质科学研究院）", "跨专业": "", "专业": "(085400)(专业学位)电子信息", "学习方式": "全日制", "研究方向": "(13)激光雷达技术", "指导老师": "", "拟招人数": "专业：47(不含推免)", "备注": "", "考试科目": {"(101)思想政治理论": "见招生简章", "(204)英语二": "见招生简章", "(302)数学二": "见招生简章", "(834)计算机专业基础（数据结构、操作系统）": "见招生简章"}}, {"招生单位": "(10357)安徽大学", "考试方式": "统考", "院系所": "(026)互联网学院", "跨专业": "", "专业": "(085400)(专业学位)电子信息", "学习方式": "全日制", "研究方向": "(01)智能感知技术及应用", "指导老师": "", "拟招人数": "专业：41(不含推免)", "备注": "", "考试科目": {"(101)思想政治理论": "见招生简章", "(201)英语一": "见招生简章", "(301)数学一": "见招生简章", "(837)数字电路与逻辑设计": "见招生简章"}}, {"招生单位": "(10357)安徽大学", "考试方式": "统考", "院系所": "(026)互联网学院", "跨专业": "", "专业": "(085400)(专业学位)电子信息", "学习方式": "全日制", "研究方向": "(02)智能信息处理及应用", "指导老师": "", "拟招人数": "专业：41(不含推免)", "备注": "", "考试科目": {"(101)思想政治理论": "见招生简章", "(201)英语一": "见招生简章", "(301)数学一": "见招生简章", "(838)数据结构": "见招生简章"}}, {"招生单位": "(10357)安徽大学", "考试方式": "统考", "院系所": "(027)联合培养（合肥综合性国家科学中心人工智能研究院）", "跨专业": "", "专业": "(085400)(专业学位)电子信息", "学习方式": "全日制", "研究方向": "(01)人工智能", "指导老师": "", "拟招人数": "专业：3(不含推免)", "备注": "", "考试科目": {"(101)思想政治理论": "见招生简章", "(201)英语一": "见招生简章", "(301)数学一": "见招生简章", "(834)计算机专业基础（数据结构、操作系统）": "见招生简章"}}]}
